forexpy/__init__.py
forexpy/backtesting/__init__.py
forexpy/backtesting/backtester.py
forexpy/backtesting/data_manager.py
forexpy/backtesting/forex_pip.py
forexpy/backtesting/grapher.py
forexpy/backtesting/position.py
forexpy/backtesting/position_manager.py
forexpy-0.0.1.dist-info/METADATA
forexpy-0.0.1.dist-info/WHEEL
forexpy-0.0.1.dist-info/top_level.txt
forexpy-0.0.1.dist-info/RECORD
