Metadata-Version: 2.1
Name: forexpy
Version: 0.0.1
Summary: Forex trading with python
Author: Carlos Lorenzo
Author-email: <clorenzozuniga@gmail.com>
Keywords: python,forex,trading,backtesting,finance
Classifier: Development Status :: 1 - Planning
Classifier: Intended Audience :: Developers
Classifier: Programming Language :: Python :: 3
Classifier: Operating System :: Unix
Classifier: Operating System :: MacOS :: MacOS X
Classifier: Operating System :: Microsoft :: Windows
Requires-Dist: pandas
Requires-Dist: mplfinance
Requires-Dist: pyaudio
